phylokit/__init__.py
phylokit/balance.py
phylokit-0.0.1a1.dist-info/LICENSE
phylokit-0.0.1a1.dist-info/METADATA
phylokit-0.0.1a1.dist-info/WHEEL
phylokit-0.0.1a1.dist-info/top_level.txt
phylokit-0.0.1a1.dist-info/RECORD
